{
    "version": "2.1.4",
    "license": "OFL-1.1",
    "homepage": "https://github.com/liberationfonts/liberation-fonts",
    "url": "https://github.com/liberationfonts/liberation-fonts/files/6418984/liberation-fonts-ttf-2.1.4.tar.gz",
    "hash": "26f85412dd0aa9d061504a1cc8aaf0aa12a70710e8d47d8b65a1251757c1a5ef",
    "extract_dir": "liberation-fonts-ttf-2.1.4",
    "checkver": {
        "github": "https://github.com/liberationfonts/liberation-fonts",
        "re": ".*/liberation-fonts/files/(?<fileno>[\\d]+)/liberation-fonts-ttf-(?<version>[\\d.]+).tar.gz"
    },
    "autoupdate": {
        "url": "https://github.com/liberationfonts/liberation-fonts/files/$matchFileno/liberation-fonts-ttf-$version.tar.gz",
        "extract_dir": "liberation-fonts-ttf-$version"
    },
    "installer": {
        "script": [
            "if(!(is_admin)) { error \"Admin rights are required, please run 'sudo scoop install $app'\"; exit 1 }",
            "Get-ChildItem $dir -filter '*.ttf' | ForEach-Object {",
            "    New-ItemProperty -Path 'HKLM:\\SOFTWARE\\Microsoft\\Windows NT\\CurrentVersion\\Fonts' -Name $_.Name.Replace($_.Extension, ' (TrueType)') -Value $_.Name -Force | Out-Null",
            "    Copy-Item $_.FullName -destination \"$env:windir\\Fonts\"",
            "}"
        ]
    },
    "uninstaller": {
        "script": [
            "if(!(is_admin)) { error \"Admin rights are required, please run 'sudo scoop uninstall $app'\"; exit 1 }",
            "Get-ChildItem $dir -filter '*.ttf' | ForEach-Object {",
            "    Remove-ItemProperty -Path 'HKLM:\\SOFTWARE\\Microsoft\\Windows NT\\CurrentVersion\\Fonts' -Name $_.Name.Replace($_.Extension, ' (TrueType)') -Force -ErrorAction SilentlyContinue",
            "    Remove-Item \"$env:windir\\Fonts\\$($_.Name)\" -Force -ErrorAction SilentlyContinue",
            "}",
            "Write-Host \"'Liberation' fonts have been uninstalled and will not be present after restarting your computer.\" -Foreground Magenta"
        ]
    }
}
